{
  "resource": "Lists",
  "resource_explanation": null,
  "http_method": "GET",
  "route": "api/lists/:id",
  "description": "Getting a specified list",
  "explanation": "Retrieves a list with reminders, by id",
  "parameters": [

  ],
  "response_fields": [

  ],
  "requests": [
    {
      "request_method": "GET",
      "request_path": "api/lists/84",
      "request_body": null,
      "request_headers": {
        "Access-Token": "p-IKifkPVsp66afRIv-7lQ",
        "Uid": "nona_parisian@schimmel.biz"
      },
      "request_query_parameters": {
      },
      "request_content_type": "application/json",
      "response_status": 200,
      "response_status_text": "OK",
      "response_body": "{\n  \"id\": 84,\n  \"title\": \"Default Reminders\",\n  \"user_id\": 42,\n  \"reminders\": [\n    {\n      \"id\": 192,\n      \"title\": \"disintermediate killer systems\",\n      \"body\": \"Stumptown tote bag tacos. Synth freegan beard. Quinoa yr +1 artisan shoreditch. Next level green juice banh mi vegan kombucha kitsch aesthetic migas. Banh mi readymade venmo humblebrag.\",\n      \"done\": true,\n      \"remind_date\": \"2017-01-12T22:35:45.353Z\",\n      \"created_at\": \"2017-01-12T21:35:48.666Z\",\n      \"updated_at\": \"2017-01-12T21:35:48.666Z\",\n      \"user_id\": null,\n      \"list_id\": 84\n    },\n    {\n      \"id\": 191,\n      \"title\": \"seize intuitive ROI\",\n      \"body\": \"Asymmetrical crucifix fap carry shoreditch literally. Franzen viral yr paleo hashtag asymmetrical. Meggings truffaut tattooed. Plaid mixtape bespoke irony direct trade cronut dreamcatcher.\",\n      \"done\": false,\n      \"remind_date\": \"2017-01-12T22:35:45.353Z\",\n      \"created_at\": \"2017-01-12T21:35:48.658Z\",\n      \"updated_at\": \"2017-01-12T21:35:48.658Z\",\n      \"user_id\": null,\n      \"list_id\": 84\n    },\n    {\n      \"id\": 190,\n      \"title\": \"generate synergistic infomediaries\",\n      \"body\": \"Mumblecore vegan crucifix butcher. Poutine tattooed keytar pickled squid before they sold out distillery. Pitchfork readymade fap hammock cred aesthetic direct trade 8-bit. Cleanse quinoa plaid yr chartreuse scenester. Thundercats goth tacos selfies portland microdosing.\",\n      \"done\": false,\n      \"remind_date\": \"2017-01-12T22:35:45.353Z\",\n      \"created_at\": \"2017-01-12T21:35:48.653Z\",\n      \"updated_at\": \"2017-01-12T21:35:48.653Z\",\n      \"user_id\": null,\n      \"list_id\": 84\n    }\n  ]\n}",
      "response_headers": {
        "access-token": "p-IKifkPVsp66afRIv-7lQ",
        "uid": "nona_parisian@schimmel.biz"
      },
      "response_content_type": "application/json; charset=utf-8",
      "curl": "curl \"api/lists/84\" -X GET \\\n\t-H \"Accept: application/json\" \\\n\t-H \"Content-Type: application/json\" \\\n\t-H \"Access-Token: p-IKifkPVsp66afRIv-7lQ\" \\\n\t-H \"Token-Type: Bearer\" \\\n\t-H \"Client: hAU2nyQpf5d_hFE0Sc_ojg\" \\\n\t-H \"Expiry: 1485466548\" \\\n\t-H \"Uid: nona_parisian@schimmel.biz\""
    }
  ]
}